PyInquirer/__init__.py
PyInquirer/color_print.py
PyInquirer/prompt.py
PyInquirer/separator.py
PyInquirer/utils.py
PyInquirer/prompts/__init__.py
PyInquirer/prompts/checkbox.py
PyInquirer/prompts/common.py
PyInquirer/prompts/confirm.py
PyInquirer/prompts/expand.py
PyInquirer/prompts/input.py
PyInquirer/prompts/list.py
PyInquirer/prompts/password.py
PyInquirer/prompts/rawlist.py
PyInquirer-1.0.2.dist-info/DESCRIPTION.rst
PyInquirer-1.0.2.dist-info/METADATA
PyInquirer-1.0.2.dist-info/RECORD
PyInquirer-1.0.2.dist-info/WHEEL
PyInquirer-1.0.2.dist-info/dependency_links.txt
PyInquirer-1.0.2.dist-info/metadata.json
PyInquirer-1.0.2.dist-info/top_level.txt
